parameter_verification/__init__.py
parameter_verification-0.1.1.dist-info/LICENSE
parameter_verification-0.1.1.dist-info/METADATA
parameter_verification-0.1.1.dist-info/WHEEL
parameter_verification-0.1.1.dist-info/top_level.txt
parameter_verification-0.1.1.dist-info/RECORD
