Metadata-Version: 2.1
Name: parameter-verification
Version: 0.1.1
Summary: Simple function that can be used to validate a list of parameters
Author-email: Thomas Dunteman <git@learningtopi.com>
Project-URL: homepage, https://www.learningtopi.com/python-modules-applications/parameter_verification
Project-URL: bug tracker, https://github.com/LearningToPi/parameter_verification/issues
Project-URL: source code, https://github.com/LearningToPi/parameter_verification
Keywords: verify,parameters
Classifier: Programming Language :: Python :: 3
Requires-Python: >=3.3
License-File: LICENSE
